kaushaltools/__init__.py
kaushaltools/encrypto.py
kaushaltools/qrmanager.py
kaushaltools/totp.py
kaushaltools-0.0.2.dist-info/LICENSE
kaushaltools-0.0.2.dist-info/METADATA
kaushaltools-0.0.2.dist-info/WHEEL
kaushaltools-0.0.2.dist-info/top_level.txt
kaushaltools-0.0.2.dist-info/RECORD
