Metadata-Version: 2.1
Name: kaushaltools
Version: 0.0.2
Summary: Making Simple to use tools with easy commands
Author: Kaushal Bhatol
Author-email: kaushal@bhatol.com
Keywords: python,tools,qrcode,encryption,data encrypt,show qr code
Classifier: Development Status :: 1 - Planning
Classifier: Intended Audience :: Developers
Classifier: Programming Language :: Python :: 3
Classifier: Operating System :: Unix
Classifier: Operating System :: MacOS :: MacOS X
Classifier: Operating System :: Microsoft :: Windows
License-File: LICENSE
Requires-Dist: qrcode
Requires-Dist: opencv-python
Requires-Dist: cryptography
Requires-Dist: json
Requires-Dist: pyotp
